adcopen/ads_client.py
adcopen/ads_manager.py
adcopen/corelink.py
adcopen/edge_triggers.py
adcopen/events.py
adcopen/sae_butterworth.py
adcopen/software_trigger.py
adcopen/ton.py
adcopen/util.py
adcopen-1.0.32.dist-info/METADATA
adcopen-1.0.32.dist-info/WHEEL
adcopen-1.0.32.dist-info/top_level.txt
adcopen-1.0.32.dist-info/RECORD
